{"Inventory":{"equiped":[null,null,null,null,null],"equipedWeapon":null,"inv":[]},"LastLocation_Save":[5.229919,-1.43475127,28.4844322],"LastSceneName":"InGame","savename":"Save638772504463841689","runsave":null,"ActionCheckList":[true,true,true,true,false,false,false,false,false,false,false,false,false,false,false,false,false,false,false,false,false,false,false,false,false,false,false,false,false,false,false,false,false,false,false,false,false,false,false,false,false,false,false,false,false,false,false,false,false,false,false,false,false,false,false,false,false,false,false,false,false,false,false,false,false,false,false,false,false,false,false,false,false,false,false,false,false,false,false,false,false,false,false,false,false,false,false,false,false,false,false,false,false,false,false,false,false,false,false,false],"ActiveMissions":[null,null,null,null,null,null,null,null,null],"CurrentMission":null,"seed":3}