{"Inventory":{"equiped":[null,null,null,null,null],"equipedWeapon":null,"inv":[]},"LastLocation_Save":[-7.40711164,-1.43475378,29.4831314],"LastSceneName":"InGame","savename":"Save638735732807639396","runsave":null,"ActionCheckList":[true,true,true,true,false,false,false,false,false,false,false,false,false,false,false,false,false,false,false,false,false,false,false,false,false,false,false,false,false,false,false,false,false,false,false,false,false,false,false,false,false,false,false,false,false,false,false,false,false,false,false,false,false,false,false,false,false,false,false,false,false,false,false,false,false,false,false,false,false,false,false,false,false,false,false,false,false,false,false,false,false,false,false,false,false,false,false,false,false,false,false,false,false,false,false,false,false,false,false,false],"ActiveMissions":[null,null,null,null,null,null,null,null,null],"CurrentMission":null,"seed":1}